Coraw/__init__.py
Coraw/coraw.py
coraw-0.1.7.dist-info/licenses/LICENSE
coraw-0.1.7.dist-info/METADATA
coraw-0.1.7.dist-info/WHEEL
coraw-0.1.7.dist-info/top_level.txt
coraw-0.1.7.dist-info/RECORD
