Metadata-Version: 2.4
Name: coraw
Version: 0.1.7
Summary: Simplest cozmo raw data sender
Home-page: https://github.com/yourname/coraw
Author: Alan
Author-email: Alan <dipdoptrip@gmail.com>
Requires-Python: >=3.8
License-File: LICENSE
Requires-Dist: pynput
Requires-Dist: inputs
Requires-Dist: opencv-python
Dynamic: author
Dynamic: home-page
Dynamic: license-file
Dynamic: requires-python
